pyronear/__init__.py
pyronear/version.py
pyronear/datasets/__init__.py
pyronear/datasets/openfire.py
pyronear/datasets/utils.py
pyronear/models/__init__.py
pyronear/models/densenet.py
pyronear/models/mobilenet.py
pyronear/models/resnet.py
pyronear/models/utils.py
pyronear/nn/__init__.py
pyronear/nn/functional.py
pyronear/nn/modules/__init__.py
pyronear/nn/modules/pooling.py
pyronear/utils/__init__.py
pyronear/utils/collect_env.py
pyronear-0.1.0.dist-info/LICENSE
pyronear-0.1.0.dist-info/METADATA
pyronear-0.1.0.dist-info/WHEEL
pyronear-0.1.0.dist-info/top_level.txt
pyronear-0.1.0.dist-info/zip-safe
pyronear-0.1.0.dist-info/RECORD
