Metadata-Version: 2.1
Name: pyronear
Version: 0.1.0
Summary: Datasets and models for wildfire detection in PyTorch
Home-page: https://github.com/frgfm/PyroNear
Author: PyroNear Contributors
Author-email: pyronear.d4g@gmail.com
Maintainer: François-Guillaume Fernandez
License: MIT
Download-URL: https://github.com/frgfm/PyroNear/tags
Keywords: pytorch,deep learning,vision,models,wildfire,object detection
Platform: UNKNOWN
Classifier: Development Status :: 4 - Beta
Classifier: Intended Audience :: Developers
Classifier: Intended Audience :: Science/Research
Classifier: License :: OSI Approved :: MIT License
Classifier: Natural Language :: English
Classifier: Operating System :: OS Independent
Classifier: Programming Language :: Python :: 3
Classifier: Programming Language :: Python :: 3.6
Classifier: Programming Language :: Python :: 3.7
Classifier: Topic :: Scientific/Engineering
Classifier: Topic :: Scientific/Engineering :: Mathematics
Classifier: Topic :: Scientific/Engineering :: Artificial Intelligence
Classifier: Topic :: Software Development
Classifier: Topic :: Software Development :: Libraries
Classifier: Topic :: Software Development :: Libraries :: Python Modules
Requires-Python: >=3.6.0
Requires-Dist: torch (>=1.2.0)
Requires-Dist: torchvision (>=0.4.0)
Requires-Dist: tqdm (>=4.20.0)
Requires-Dist: requests (>=2.20.0)
